README.rst
setup.cfg
setup.py
exopy_pulses/__init__.py
exopy_pulses/version.py
exopy_pulses.egg-info/PKG-INFO
exopy_pulses.egg-info/SOURCES.txt
exopy_pulses.egg-info/dependency_links.txt
exopy_pulses.egg-info/entry_points.txt
exopy_pulses.egg-info/not-zip-safe
exopy_pulses.egg-info/requires.txt
exopy_pulses.egg-info/top_level.txt
exopy_pulses/measurement/__init__.py
exopy_pulses/measurement/manifest.enaml
exopy_pulses/measurement/editors/__init__.py
exopy_pulses/measurement/editors/pulses_editor.enaml
exopy_pulses/pulses/__init__.py
exopy_pulses/pulses/api.py
exopy_pulses/pulses/declarations.py
exopy_pulses/pulses/dependencies_analysis.enaml
exopy_pulses/pulses/filters.py
exopy_pulses/pulses/infos.py
exopy_pulses/pulses/item.py
exopy_pulses/pulses/manifest.enaml
exopy_pulses/pulses/plugin.py
exopy_pulses/pulses/pulse.py
exopy_pulses/pulses/pulse_view.enaml
exopy_pulses/pulses/configs/__init__.py
exopy_pulses/pulses/configs/base_config.py
exopy_pulses/pulses/configs/base_config_views.enaml
exopy_pulses/pulses/configs/template_config.py
exopy_pulses/pulses/configs/template_config_view.enaml
exopy_pulses/pulses/contexts/__init__.py
exopy_pulses/pulses/contexts/base_context.py
exopy_pulses/pulses/contexts/template_context.py
exopy_pulses/pulses/contexts/views/__init__.py
exopy_pulses/pulses/contexts/views/base_context_view.enaml
exopy_pulses/pulses/contexts/views/template_context_view.enaml
exopy_pulses/pulses/sequences/__init__.py
exopy_pulses/pulses/sequences/base_sequences.py
exopy_pulses/pulses/sequences/conditional_sequence.py
exopy_pulses/pulses/sequences/repeat_sequence.py
exopy_pulses/pulses/sequences/template_sequence.py
exopy_pulses/pulses/sequences/views/__init__.py
exopy_pulses/pulses/sequences/views/abstract_sequence_view.enaml
exopy_pulses/pulses/sequences/views/base_sequences_views.enaml
exopy_pulses/pulses/sequences/views/conditional_view.enaml
exopy_pulses/pulses/sequences/views/sequence_editor_view.enaml
exopy_pulses/pulses/sequences/views/template_view.enaml
exopy_pulses/pulses/shapes/__init__.py
exopy_pulses/pulses/shapes/base_shape.py
exopy_pulses/pulses/shapes/modulation.py
exopy_pulses/pulses/shapes/slope_shape.py
exopy_pulses/pulses/shapes/square_shape.py
