Metadata-Version: 1.1
Name: exopy-pulses
Version: 0.1.0
Summary: ExopyPulses plugin package
Home-page: https://github.com/exopy/exopy_pulses
Author: see AUTHORS
Author-email: m.dartiailh@gmail.com
License: BSD
Download-URL: https://github.com/exopy/exopy_pulses/tarball/master
Keywords: experiment automation GUI
Platform: UNKNOWN
Classifier: Development Status :: 3 - Alpha
Classifier: License :: OSI Approved :: BSD License
Classifier: Natural Language :: English
Classifier: Operating System :: OS Independent
Classifier: Topic :: Scientific/Engineering :: Physics
Classifier: Programming Language :: Python :: 2.7
Classifier: Programming Language :: Python :: 3.5
Classifier: Programming Language :: Python :: 3.6
Requires: exopy
Requires: numpy
